{
  "data": [
    {
      "title": "a CLASSIC",
      "body": "My purchase of the JanSport Fifth Avenue Fanny Pack has been a nostalgic and practical addition to my everyday essentials.\n\nThis classic fanny pack is a testament to JanSport's enduring quality. The compact design and durable material make it an ideal choice for carrying essentials without the bulk of a traditional bag. The simplicity and functionality of the pack harken back to a timeless era, reminding me of its enduring appeal.\n\nThe spacious main compartment easily accommodates my wallet, keys, and other small items, making it perfect for on-the-go activities. The adjustable waist strap ensures a comfortable fit, and the iconic JanSport logo adds a touch of retro charm.\n\nFor those seeking a reliable and stylish accessory, the JanSport Fifth Avenue Fanny Pack is a classic choice that stands the test of time. It effortlessly combines functionality with a touch of nostalgia, making it a versatile and enduring addition to any wardrobe.",
      "rating": 5,
      "hasImage": 0,
      "hasVideo": 0,
      "isAI": 1
    }
  ]
}