{
  "data": [
    {
      "title": "Upgrade Your Home Security with the Stylish Ring Video Doorbell in Venetian Bronze",
      "body": "Alright, folks, let's chat about the Ring Video Doorbell in Venetian Bronze. First off, can we just talk about how sleek and stylish this thing looks? The venetian bronze finish adds a touch of elegance to any doorway, seriously elevating your home's curb appeal. But it's not just about looks – this doorbell means serious business when it comes to home security. The setup was a breeze, even for a tech newbie like me. Within minutes, I had it installed and synced up to my smartphone 📱. And let me tell you, the video quality is top-notch. I can see crystal clear footage of anyone who approaches my door, day or night. The motion detection feature is a game-changer too – I get instant alerts whenever someone steps foot on my porch. Plus, the two-way audio lets me communicate with visitors even when I'm not home. Oh, and did I mention the convenience of being able to check on my doorstep from anywhere? Whether I'm at work or on vacation, I can keep tabs on what's happening at home with just a tap of my finger. Talk about peace of mind Plus, the Ring app is super user-friendly and packed with handy features. And let's not forget about the community aspect – being able to share and view neighborhood alerts adds an extra layer of security. Overall, I couldn't be happier with my Ring Video Doorbell in Venetian Bronze. It's stylish, it's smart, and it's seriously stepped up my home security game. Worth every penny and then some!",
      "rating": 5,
      "hasImage": 1,
      "hasVideo": 0,
      "isAI": 1
    }
  ]
}