{
	"data": [
		{
			"title": "Tastes Like Sugar, but Pricier",
			"body": "Lakanto Monkfruit Sweetener is an exciting discovery for those looking to cut back on sugar without sacrificing taste. It's impressively similar to regular sugar, and here's why:\n\nPros:\n\nTaste: The standout feature of this sweetener is that it truly tastes like sugar. It's rare to find a sugar substitute without an aftertaste, but Lakanto has nailed it.\n\nNo Sugar, No Calories: For those monitoring their sugar intake or trying to lose weight, this sweetener is a game-changer. It's a guilt-free way to satisfy your sweet tooth.\n\nVersatility: This sweetener is suitable for cooking, baking, and sweetening beverages. It's a functional and tasty alternative to sugar in almost any context.\n\nNatural Ingredients: Derived from monk fruit, it's reassuring to know that this sweetener doesn't contain artificial chemicals. It's an option that many health-conscious consumers appreciate.\n\nCons:\n\nPrice: While the taste and benefits are noteworthy, the cost can be a barrier for some. It's significantly more expensive than regular sugar, which may limit its appeal for daily use.\nConclusion:\n\nLakanto Monkfruit Sweetener has managed to create a product that genuinely tastes like sugar, and for that alone, it's worth trying. Though the price might deter some, those looking for a healthy sugar substitute without sacrificing flavor may find this to be the perfect solution. It's a high-quality product that delivers on its promise, and I highly recommend giving it a try if you're in the market for a sugar alternative.",
			"rating": 5,
			"hasImage": 0,
			"hasVideo": 0,
			"isAI": 1
		}
	]
}
