{
	"data": [
		{
			"title": "Comfortable, Stylish, and Functional - Ideal Swim Trunks for Resort-Goers",
			"body": "I recently purchased the maamgic Mens Swim Trunks and have been thoroughly impressed with their performance. The standout feature for me is the 2-in-1 compression liner. I've always preferred compression wear over traditional mesh liners, and these trunks offer a comfortable, chafe-free experience. I've worn them for extended periods (over 6 hours) without any discomfort.\n\nThe 5.5\" inseam hits the sweet spot in terms of length. It's perfect for current fashion trends, hitting mid-thigh, and offers a great balance between coverage and freedom of movement. The compression liner adds an extra layer of coverage, ensuring everything stays in place while on the move.\n\nThe secure zipper pockets are a game changer, especially when at hotels and resorts. They provide a safe place to store personal items like cards and keys, which is incredibly convenient.\n\nAnother impressive feature is the quick-dry fabric. These trunks transition from wet to dry in under an hour, which is perfect for those days spent in and out of the water. The fabric's blend of 90% polyester and 10% spandex offers flexibility and comfort, allowing for unrestricted movement.\n\nThe elastic waistband and drawstring are easy to adjust for a snug fit. My only minor critique is the length of the drawstrings; I wish they were a bit longer for more secure tying.\n\nOverall, the quality of these swim trunks is exceptional. They're a great combination of style, comfort, and functionality. I would definitely recommend these trunks, especially for those who frequent pools, beaches, or resorts. They're a fantastic investment for anyone looking for a comfortable, stylish, and practical swimwear option.",
			"rating": 5,
			"hasImage": 0,
			"hasVideo": 0,
			"isAI": 1
		}
	]
}
