{
  "data": [
    {
      "title": "Epic Gaming Awaits - PS5/God of War Ragnarök Bundle Review",
      "body": "The PS5 Digital Edition God of War Ragnarök Bundle is the ultimate gaming package that combines the power of the PlayStation 5 with one of the most highly anticipated games of the year. As a gaming enthusiast, I can attest that this bundle delivers an unparalleled gaming experience that will leave you in awe.\n\nPS5 Digital Edition - Next-Gen Gaming at Its Best\n\nThe standout feature of this bundle is the PlayStation 5 Digital Edition, Sony's latest and most advanced gaming console. With its lightning-fast load times, stunning 4K graphics, and immersive 3D audio, the PS5 sets a new standard for gaming.\n\nThe PS5 Digital Edition is known for its sleek design and compact form factor. It fits seamlessly into your entertainment center while delivering breathtaking visuals and incredible performance. The absence of a physical disc drive makes it even more streamlined and perfect for gamers who prefer digital downloads.\n\nOne of the most significant advantages of the PS5 is its extensive library of games, many of which are optimized for the console's power. From immersive open-world adventures to heart-pounding action titles, there's something for every gamer. The PlayStation Store offers a vast selection of digital games, and with the included PlayStation Plus membership, you gain access to a collection of free games every month.\n\nThe DualSense wireless controller is a game-changer, featuring haptic feedback and adaptive triggers that provide a level of immersion you've never experienced before. Playing games on the PS5 feels incredibly responsive and realistic, enhancing every gaming session.\n\nGod of War Ragnarök - An Epic Adventure\n\nThe crown jewel of this bundle is undoubtedly God of War Ragnarök, the highly anticipated sequel to the critically acclaimed God of War (2018). In this epic Norse mythology-inspired adventure, you step into the shoes of Kratos and embark on a journey filled with gods, monsters, and legendary battles.\n\nThe game's standout feature is its breathtaking storytelling and character development. The relationship between Kratos and his son, Atreus, adds emotional depth to the narrative, making it more than just a hack-and-slash adventure. The game's world is vast and immersive, with stunning visuals and an epic soundtrack that draws you into the Norse realm.\n\nCombat in God of War Ragnarök is intense and satisfying, with a variety of weapons and abilities at your disposal. Whether you're facing off against gods or battling mythical creatures, each encounter is a cinematic and adrenaline-pumping experience.\n\nThe Perfect Bundle for Gamers\n\nTogether, the PS5 Digital Edition and God of War Ragnarök create a gaming experience that is second to none. The power of the PS5 enhances the visuals and performance of the game, making it a truly next-gen experience.\n\nIn conclusion, the PS5 Digital Edition God of War Ragnarök Bundle is a must-have for any gaming enthusiast. It combines the cutting-edge technology of the PS5 with the epic storytelling of God of War Ragnarök, delivering an unforgettable gaming journey. Whether you're a long-time fan of the series or a newcomer to the world of PlayStation, this bundle offers an exceptional value that will keep you entertained for countless hours. Don't miss out on the opportunity to embark on this epic gaming adventure.",
      "rating": 5,
      "hasImage": 0,
      "hasVideo": 0,
      "isAI": 1
    }
  ]
}