{
  "data": [
    {
      "title": "Nespresso VertuoPlus Deluxe: Your Ultimate Coffee Experience",
      "body": "The Nespresso VertuoPlus Deluxe by De'Longhi in Titan is a coffee and espresso lover's dream. With its sleek design and innovative technology, it delivers barista-quality beverages at the touch of a button. The included Vertuoline Variety Pack adds an exciting array of flavors to your coffee repertoire. Say hello to your new favorite morning ritual.",
      "rating": 5,
      "hasImage": 0,
      "hasVideo": 0,
      "isAI": 1
    }
  ]
}