{
	"data": [
		{
			"title": "A Near-Perfect Manicure Set",
			"body": "I recently acquired a new manicure set, and it has quickly become an integral part of my personal care routine. While it's near perfect, there's one small caveat, hence my 4.5-star rating.\n\nThe quality of each tool in this set is excellent. From the nail clippers to the cuticle pushers, each piece is made with care and precision, ensuring a clean and hassle-free manicure at home. The tools are sharp where they need to be, yet safe to use, making them perfect for both beginners and seasoned users.\n\nOne feature that stands out is the comfort and ease of handling. Each tool is ergonomically designed, allowing for precise control and reducing the risk of accidental slips or nicks. This quality craftsmanship extends to the case too. It's stylish and compact, ideal for both home use and travel.\n\nHowever, it's this compactness that brings me to the minor issue I've found with this set. Given its small size, it's quite easy to misplace or lose, especially when traveling. If you're someone who tends to forget where they put things or if you're constantly on the go, this is something to consider. Perhaps attaching a brightly colored tag or a keyring could be a solution to keep track of it better.\n\nThat being said, this minor inconvenience doesn't detract from the overall excellence of the manicure set. The tools are durable and effective, making nail care a breeze. They've retained their sharpness and functionality even with regular use, a testament to their quality.\n\nIn conclusion, if you're in the market for a manicure set that provides professional-level care at home, this product is a fantastic choice. Just remember to keep an eye on it due to its small size. Despite this minor flaw, this manicure set stands out in the crowded field of personal care products and is certainly worth the investment.",
			"rating": 4,
			"hasImage": 0,
			"hasVideo": 0,
			"isAI": 2
		}
	]
}
