{
  "data": [
    {
      "title": "Restful nights",
      "body": "I recently had the pleasure of sleeping on a Deluxe Air Mattress, and it has completely transformed my view on temporary bedding solutions. The most notable aspect of this air mattress is the unparalleled comfort it offers. For the first time, I was able to sleep through the entire night on an air mattress without any discomfort or the usual tossing and turning.\n\nThe mattress felt stable and supportive, mimicking the feel of a traditional bed. Its deluxe design provided a perfect balance between firmness and softness, ensuring that my sleep was restful and uninterrupted. The ease of inflating and deflating the mattress is also worth mentioning, making it an excellent choice for guests or travel.\n\nFor anyone in need of a portable yet comfortable sleeping option, the Deluxe Air Mattress is a fantastic choice. It proves that you don’t have to compromise on comfort, even when you’re away from your regular bed.",
      "rating": 5,
      "hasImage": 0,
      "hasVideo": 0,
      "isAI": 1
    }
  ]
}