{
  "data": [
    {
      "title": "Power Your Devices Reliably with Duracell 2450 3V Lithium Battery",
      "body": "Ensure your medical devices and fitness gadgets stay powered and ready for action with the Duracell 2450 3V Lithium Battery. Designed to deliver long-lasting and dependable performance, this lithium coin battery is the ideal choice for a wide range of devices, including medical monitors, fitness trackers, and more. Here's why the Duracell 2450 3V Lithium Battery is the perfect solution for your power needs:\n\nReliable Performance for Your Devices (5/5):\nTrust in the consistent and reliable performance of the Duracell 2450 3V Lithium Battery, which is engineered to power your essential devices with precision and efficiency. Whether you're monitoring your health or tracking your fitness goals, this battery provides the dependable power you need to keep your devices running smoothly.\n\nLong-Lasting Power (5/5):\nEnjoy peace of mind with the long-lasting power of the Duracell 2450 3V Lithium Battery, which is designed to provide extended usage time for your medical and fitness devices. With its high energy density and low self-discharge rate, this battery ensures that your devices stay powered for longer, reducing the need for frequent replacements.\n\nVersatile Compatibility (5/5):\nExperience versatile compatibility with the Duracell 2450 3V Lithium Battery, which is compatible with a wide range of devices, including medical monitors, glucose meters, heart rate monitors, pedometers, and more. Whether you're managing a chronic condition or tracking your fitness progress, this battery offers the versatility and reliability you need for your devices.\n\nCompact and Lightweight Design (5/5):\nBenefit from the compact and lightweight design of the Duracell 2450 3V Lithium Battery, which makes it easy to carry spares for on-the-go convenience. Whether you're traveling, exercising outdoors, or simply keeping a backup on hand, this battery's portable design ensures that you're always prepared for any power needs that may arise.\n\nTrusted Duracell Quality (5/5):\nRely on the trusted quality and performance of Duracell, a brand that has been delivering innovative battery solutions for decades. Backed by years of expertise and a commitment to excellence, the Duracell 2450 3V Lithium Battery upholds the brand's legacy of reliability and durability, ensuring that your devices receive the power they need to perform at their best.\n\nConclusion: Power Your Devices with Confidence with Duracell 2450 3V Lithium Battery\n\nIn conclusion, the Duracell 2450 3V Lithium Battery is the perfect choice for powering your medical and fitness devices with confidence and reliability. With its dependable performance, long-lasting power, versatile compatibility, compact design, and trusted Duracell quality, this battery ensures that your devices stay powered and ready for action whenever you need them. Keep your devices running smoothly and efficiently with Duracell 2450 3V Lithium Battery.",
      "rating": 5,
      "hasImage": 0,
      "hasVideo": 0,
      "isAI": 1
    }
  ]
}