{
  "data": [
    {
      "title": "Purr-fect Gift for Golf Enthusiasts: #N/A Lucky Cat Putter Head Cover Delights avid Golfer!",
      "body": "When searching for the perfect gift for my brother, an avid golfer, I stumbled upon the Lucky Cat Putter Head Cover, and it turned out to be a hole-in-one choice!\n\nFirst and foremost, let's talk about the design. The charming lucky cat motif adds a whimsical touch to his golf bag, standing out amidst the sea of ordinary head covers on the course. The vibrant colors and intricate details of the cat's expression bring a smile to his face every time he retrieves his putter.\n\nBeyond its aesthetic appeal, this head cover offers practical benefits as well. The durable construction provides reliable protection for his putter, safeguarding it from scratches and dings during transportation and storage. The secure fit ensures that the cover stays in place, giving him peace of mind on the course.\n\nAs an avid golfer, my brother appreciates the thoughtfulness behind this gift. It's not just a head cover; it's a symbol of good luck and a reminder to approach each putt with confidence and positivity. Plus, the unique design sparks conversations with fellow golfers, further enhancing his enjoyment of the game.\n\nIn summary, the Lucky Cat Putter Head Cover is a delightful gift for any golf enthusiast, especially those who appreciate a touch of whimsy on the course. With its charming design, durable construction, and practical functionality, it's sure to bring joy to any golfer's game. Trust me, once you gift this head cover, you'll earn a spot in the winner's circle of gift-giving!",
      "rating": 5,
      "hasImage": 0,
      "hasVideo": 0,
      "isAI": 1
    }
  ]
}